movee/__init__.py
movee/__main__.py
movee/cast.py
movee/cast_recorder.py
movee/config.py
movee/constants.py
movee/line.py
movee/movee.py
movee/parse.py
movee/prompt.py
movee/render.py
movee/run.py
movee/stable_hash.py
movee/times.py
movee/typing_errors.py
movee/upload.py
movee/validate.py
movee/waiter.py
movee-0.10.0.dist-info/LICENSE
movee-0.10.0.dist-info/WHEEL
movee-0.10.0.dist-info/METADATA
movee-0.10.0.dist-info/RECORD
